botocraft/__init__.py
botocraft/main.py
botocraft/py.typed
botocraft/cli/__init__.py
botocraft/cli/botocore.py
botocraft/cli/cli.py
botocraft/cli/data.py
botocraft/cli/shell.py
botocraft/cli/sync.py
botocraft/eventbridge/__init__.py
botocraft/eventbridge/base.py
botocraft/eventbridge/ecr.py
botocraft/eventbridge/ecs.py
botocraft/eventbridge/factory.py
botocraft/eventbridge/raw/__init__.py
botocraft/eventbridge/raw/ecr/__init__.py
botocraft/eventbridge/raw/ecr/aws_api_call_via_cloudtrail.py
botocraft/eventbridge/raw/ecr/ecr_image_action.py
botocraft/eventbridge/raw/ecr/ecr_image_scan.py
botocraft/eventbridge/raw/ecr/pull_through_cache_action.py
botocraft/eventbridge/raw/ecr/referrer_action.py
botocraft/eventbridge/raw/ecr/replication_action.py
botocraft/eventbridge/raw/ecr/scan_resource_change.py
botocraft/eventbridge/raw/ecs/__init__.py
botocraft/eventbridge/raw/ecs/aws_api_call_via_cloudtrail.py
botocraft/eventbridge/raw/ecs/container_instance_change.py
botocraft/eventbridge/raw/ecs/service_action.py
botocraft/eventbridge/raw/ecs/service_deployment_state_change.py
botocraft/eventbridge/raw/ecs/task_state_change.py
botocraft/mixins/__init__.py
botocraft/mixins/application_autoscaling.py
botocraft/mixins/autoscaling.py
botocraft/mixins/ec2.py
botocraft/mixins/ecr.py
botocraft/mixins/ecs.py
botocraft/mixins/elasticache.py
botocraft/mixins/elb.py
botocraft/mixins/elbv2.py
botocraft/mixins/events.py
botocraft/mixins/iam.py
botocraft/mixins/inspector2.py
botocraft/mixins/kms.py
botocraft/mixins/route53.py
botocraft/mixins/s3.py
botocraft/mixins/sqs.py
botocraft/mixins/tags.py
botocraft/services/__init__.py
botocraft/services/abstract.py
botocraft/services/application_autoscaling.py
botocraft/services/autoscaling.py
botocraft/services/common.py
botocraft/services/ec2.py
botocraft/services/ecr.py
botocraft/services/ecs.py
botocraft/services/elasticache.py
botocraft/services/elb.py
botocraft/services/elbv2.py
botocraft/services/events.py
botocraft/services/exceptions.py
botocraft-0.21.7.dist-info/licenses/LICENSE.txt
botocraft-0.21.7.dist-info/METADATA
botocraft-0.21.7.dist-info/WHEEL
botocraft-0.21.7.dist-info/entry_points.txt
botocraft-0.21.7.dist-info/top_level.txt
botocraft-0.21.7.dist-info/RECORD
